.DS_Store
imgtojp2.py
kdu_jp2/__init__.py
kdu_jp2/jp2converter.py
kdu_jp2-1.2.data/scripts/imgtojp2
kdu_jp2-1.2.dist-info/LICENSE
kdu_jp2-1.2.dist-info/METADATA
kdu_jp2-1.2.dist-info/WHEEL
kdu_jp2-1.2.dist-info/top_level.txt
kdu_jp2-1.2.dist-info/RECORD
